fucker/fucker.py
fucktheimage-4.0.0.dist-info/METADATA
fucktheimage-4.0.0.dist-info/WHEEL
fucktheimage-4.0.0.dist-info/top_level.txt
fucktheimage-4.0.0.dist-info/RECORD
