Metadata-Version: 2.1
Name: fucktheimage
Version: 4.0.0
Summary: 一个免费而简单图床(喜欢就关注:python学霸微信公众号)
Home-page: UNKNOWN
Author: Python学霸
Author-email: python@xueba.com
License: UNKNOWN
Platform: UNKNOWN
Requires-Dist: requests
